img/bin/fullAdder.v
module fullAdder(input wire a,b,c,output wire y);
    wire t1,t2,t3;
    assign t1 = ~c;
    assign t2 = a & t1;
    assign t3 = b & c;
    assign y = t2|t3;
endmodule

img/bin/tb_fullAdder.v
module tb_fullAdder;
reg t_a,t_b,t_c;
wire t_y;
fullAdder ckt1(.a(t_a),.b(t_b),.c(t_c),.y(t_y));
initial begin
    $dumpfile("1.vcd");
    $dumpvars(0,tb_fullAdder);
end
initial begin
    $monitor(t_a,t_b,t_c,t_y);
    t_a = 1'b0; t_b = 1'b0;t_c = 1'b0; //000
    #5   
    t_a = 1'b0;t_b = 1'b0; t_c = 1'b1; //001
    #5
    t_a = 1'b0;t_b = 1'b1;t_c = 1'b0; //010   
    #5 
    t_a = 1'b0;t_b = 1'b1; t_c = 1'b1; //011
    #5 
    t_a = 1'b1;t_b = 1'b0;t_c = 1'b0; //100
    #5  
    t_a = 1'b1;t_b = 1'b0;t_c = 1'b1; //101
    #5    
    t_a = 1'b1;t_b = 1'b1;t_c = 1'b0; //110
    #5   
    t_a = 1'b1;t_b = 1'b1;t_c = 1'b1; //111
    #5        
    t_a = 1'b0;t_b = 1'b0;   t_c = 1'b0; //000 
end    
endmodule

img/bin/1.vcd
$date
	Sun Aug 20 21:48:33 2023
$end
$version
	Icarus Verilog
$end
$timescale
	1s
$end
$scope module tb_fullAdder $end
$var wire 1 ! t_y $end
$var reg 1 " t_a $end
$var reg 1 # t_b $end
$var reg 1 $ t_c $end
$scope module ckt1 $end
$var wire 1 % a $end
$var wire 1 & b $end
$var wire 1 ' c $end
$var wire 1 ( t1 $end
$var wire 1 ) t2 $end
$var wire 1 * t3 $end
$var wire 1 ! y $end
$upscope $end
$upscope $end
$enddefinitions $end
#0
$dumpvars
0*
0)
1(
0'
0&
0%
0$
0#
0"
0!
$end
#5
0(
1$
1'
#10
1(
0$
0'
1#
1&
#15
1!
0(
1*
1$
1'
#20
1)
1!
1(
0*
0$
0'
0#
0&
1"
1%
#25
0!
0)
0(
1$
1'
#30
1!
1)
1(
0$
0'
1#
1&
#35
0)
0(
1*
1$
1'
#40
0!
1(
0*
0$
0'
0#
0&
0"
0%
